kare/__init__.py
kare/curry.py
kare/functions.py
kare-0.0.1.dist-info/WHEEL
kare-0.0.1.dist-info/METADATA
kare-0.0.1.dist-info/RECORD
