Metadata-Version: 2.1
Name: kare
Version: 0.0.1
Summary: Minimalist Currying implementation for Python
Home-page: https://github.com/Beetelbrox/kare
License: MIT
Keywords: functional,functional programming,fp,curry,currying
Author: Francisco J. Jurado
Author-email: 9376816+Beetelbrox@users.noreply.github.com
Requires-Python: >=3.9,<4.0
Classifier: License :: OSI Approved :: MIT License
Classifier: Programming Language :: Python :: 3
Classifier: Programming Language :: Python :: 3.10
Classifier: Programming Language :: Python :: 3.9
Project-URL: Repository, https://github.com/Beetelbrox/kare
